setup.cfg
setup.py
pacpy/__init__.py
pacpy/filt.py
pacpy/pac.py
pacpy/util.py
pacpy.egg-info/PKG-INFO
pacpy.egg-info/SOURCES.txt
pacpy.egg-info/dependency_links.txt
pacpy.egg-info/requires.txt
pacpy.egg-info/top_level.txt
pacpy/tests/exampledata.npy
pacpy/tests/test_filt.py
pacpy/tests/test_pac.py