Metadata-Version: 1.1
Name: pacpy
Version: 1.0
Summary: A module to calculate phase-amplitude coupling
Home-page: https://github.com/voytekresearch/pacpy
Author: The Voytek Lab
Author-email: voyteklab@gmail.com
License: MIT
Download-URL: https://github.com/voytekresearch/pacpy/archive/v1.0.tar.gz
Keywords: neuroscience spectral phase-amplitude
Platform: UNKNOWN
Classifier: Intended Audience :: Science/Research
Classifier: License :: OSI Approved
Classifier: Programming Language :: Python
Classifier: Topic :: Scientific/Engineering
Classifier: Operating System :: Microsoft :: Windows
Classifier: Operating System :: POSIX
Classifier: Operating System :: Unix
Classifier: Operating System :: MacOS
Classifier: Programming Language :: Python :: 2
Classifier: Programming Language :: Python :: 2.6
Classifier: Programming Language :: Python :: 2.7
